{
  "ignorePatterns": [
    {
      "pattern": "^https://img\\.shields\\.io/"
    },
    {
      "pattern": "^https://github\\.com/linuxfoundation/lfx-v2-ui"
    },
    {
      "pattern": "^https://github\\.com/mlehotskylf"
    },
    {
      "pattern": "^/images/",
      "comment": "App-relative image paths served by the Nuxt frontend (frontend/public/images/) — not resolvable by offline link checkers"
    },
    {
      "pattern": "^/for-companies",
      "comment": "App-relative route (frontend/app/pages/for-companies.vue) — not resolvable by offline link checkers"
    },
    {
      "pattern": "^https://crowdfunding\\.linuxfoundation\\.org/images/docs/",
      "comment": "Docs screenshot images served from the production LFX Crowdfunding site — not yet available in CI (site not yet deployed to production)"
    },
    {
      "pattern": "^https://app\\.lfx\\.dev/",
      "comment": "Requires Auth0 SSO login — unreachable by an unauthenticated link checker"
    }
  ],
  "timeout": "20s",
  "retryOn429": true,
  "retryCount": 3
}
